hello.py
charlie_pop_hello-0.0.22.dist-info/DESCRIPTION.rst
charlie_pop_hello-0.0.22.dist-info/METADATA
charlie_pop_hello-0.0.22.dist-info/RECORD
charlie_pop_hello-0.0.22.dist-info/WHEEL
charlie_pop_hello-0.0.22.dist-info/entry_points.txt
charlie_pop_hello-0.0.22.dist-info/metadata.json
charlie_pop_hello-0.0.22.dist-info/top_level.txt
