Metadata-Version: 2.0
Name: charlie-pop-hello
Version: 0.0.22
Summary: A module to say hello
Home-page: https://github.com/charlieallatson/hello_world
Author: Charlie Allatson
Author-email: charles.allatson@gmail.com
License: MIT
Platform: UNKNOWN
